knoxnl/__init__.py
knoxnl/knoxnl.py
knoxnl-5.6.dist-info/LICENSE
knoxnl-5.6.dist-info/METADATA
knoxnl-5.6.dist-info/WHEEL
knoxnl-5.6.dist-info/entry_points.txt
knoxnl-5.6.dist-info/top_level.txt
knoxnl-5.6.dist-info/RECORD
