Metadata-Version: 2.1
Name: knoxnl
Version: 5.6
Summary: A python wrapper around the amazing KNOXSS API by Brute Logic (requires an API Key)
Home-page: https://github.com/xnl-h4ck3r/knoxnl
Author: @xnl-h4ck3r
License-File: LICENSE
Requires-Dist: requests
Requires-Dist: termcolor
Requires-Dist: pyaml
Requires-Dist: urlparse3
Requires-Dist: python-dateutil
